tornado_openapi/MetaManager.py
tornado_openapi/OpenApiConfiguration.py
tornado_openapi/OpenApiConfigurator.py
tornado_openapi/OpenApiHandler.py
tornado_openapi/__init__.py
tornado_openapi/decorators/__init__.py
tornado_openapi/decorators/anonymous.py
tornado_openapi/decorators/api.py
tornado_openapi/decorators/apiKey.py
tornado_openapi/decorators/bearerToken.py
tornado_openapi/decorators/cookie.py
tornado_openapi/decorators/header.py
tornado_openapi/decorators/httpBasic.py
tornado_openapi/decorators/mutualTLS.py
tornado_openapi/decorators/oauth2.py
tornado_openapi/decorators/openId.py
tornado_openapi/decorators/request.py
tornado_openapi/decorators/response.py
tornado_openapi/objects/Callback.py
tornado_openapi/objects/Components.py
tornado_openapi/objects/Contact.py
tornado_openapi/objects/DescriptionObject.py
tornado_openapi/objects/Discriminator.py
tornado_openapi/objects/Encoding.py
tornado_openapi/objects/Example.py
tornado_openapi/objects/ExternalDocumentation.py
tornado_openapi/objects/Header.py
tornado_openapi/objects/Info.py
tornado_openapi/objects/License.py
tornado_openapi/objects/Link.py
tornado_openapi/objects/MediaType.py
tornado_openapi/objects/OAuthFlow.py
tornado_openapi/objects/OAuthFlows.py
tornado_openapi/objects/OpenAPI.py
tornado_openapi/objects/Operation.py
tornado_openapi/objects/Parameter.py
tornado_openapi/objects/ParameterLocation.py
tornado_openapi/objects/ParameterStyle.py
tornado_openapi/objects/PathItem.py
tornado_openapi/objects/Paths.py
tornado_openapi/objects/Reference.py
tornado_openapi/objects/RequestBody.py
tornado_openapi/objects/Response.py
tornado_openapi/objects/Responses.py
tornado_openapi/objects/Schema.py
tornado_openapi/objects/SecurityRequirement.py
tornado_openapi/objects/SecurityScheme.py
tornado_openapi/objects/Server.py
tornado_openapi/objects/ServerVariable.py
tornado_openapi/objects/Tag.py
tornado_openapi/objects/Xml.py
tornado_openapi/objects/__init__.py
tornado_openapi-0.1.4.dist-info/licenses/LICENSE
tornado_openapi-0.1.4.dist-info/METADATA
tornado_openapi-0.1.4.dist-info/WHEEL
tornado_openapi-0.1.4.dist-info/top_level.txt
tornado_openapi-0.1.4.dist-info/RECORD
